{"/*":["X-Frame-Options: DENY","X-XSS-Protection: 1; mode=block","X-Content-Type-Options: nosniff","Referrer-Policy: same-origin"],"/commons-3745144e6a5b7d0ac6bc.js":["Cache-Control: public, max-age=31536000, immutable"],"/component---node-modules-lekoarts-gatsby-theme-cara-src-templates-cara-tsx-ae2fb4acb76fe1784381.js":["Cache-Control: public, max-age=31536000, immutable"],"/component---src-pages-404-jsx-c1fdcfa3608d4f11368c.js":["Cache-Control: public, max-age=31536000, immutable"],"/webpack-runtime-ba2b5c6a4c0cedc6e54b.js":["Cache-Control: public, max-age=31536000, immutable"],"/framework-4f407f1f96c7c1fe9b9f.js":["Cache-Control: public, max-age=31536000, immutable"],"/app-1c7d4fffcd4d1e1b7004.js":["Cache-Control: public, max-age=31536000, immutable"],"/static/*":["Cache-Control: public, max-age=31536000, immutable"],"/sw.js":["Cache-Control: public, max-age=0, must-revalidate"],"/":["Link: </webpack-runtime-ba2b5c6a4c0cedc6e54b.js>; rel=preload; as=script; nopush","Link: </framework-4f407f1f96c7c1fe9b9f.js>; rel=preload; as=script; nopush","Link: </app-1c7d4fffcd4d1e1b7004.js>; rel=preload; as=script; nopush","Link: </commons-3745144e6a5b7d0ac6bc.js>; rel=preload; as=script; nopush","Link: </component---node-modules-lekoarts-gatsby-theme-cara-src-templates-cara-tsx-ae2fb4acb76fe1784381.js>; rel=preload; as=script; nopush","Link: </page-data/app-data.json>; rel=preload; as=fetch; crossorigin; nopush","Link: </page-data/index/page-data.json>; rel=preload; as=fetch; crossorigin; nopush"],"/404/":["Link: </webpack-runtime-ba2b5c6a4c0cedc6e54b.js>; rel=preload; as=script; nopush","Link: </framework-4f407f1f96c7c1fe9b9f.js>; rel=preload; as=script; nopush","Link: </app-1c7d4fffcd4d1e1b7004.js>; rel=preload; as=script; nopush","Link: </commons-3745144e6a5b7d0ac6bc.js>; rel=preload; as=script; nopush","Link: </component---src-pages-404-jsx-c1fdcfa3608d4f11368c.js>; rel=preload; as=script; nopush","Link: </page-data/app-data.json>; rel=preload; as=fetch; crossorigin; nopush","Link: </page-data/404/page-data.json>; rel=preload; as=fetch; crossorigin; nopush"],"/404.html":["Link: </webpack-runtime-ba2b5c6a4c0cedc6e54b.js>; rel=preload; as=script; nopush","Link: </framework-4f407f1f96c7c1fe9b9f.js>; rel=preload; as=script; nopush","Link: </app-1c7d4fffcd4d1e1b7004.js>; rel=preload; as=script; nopush","Link: </commons-3745144e6a5b7d0ac6bc.js>; rel=preload; as=script; nopush","Link: </component---src-pages-404-jsx-c1fdcfa3608d4f11368c.js>; rel=preload; as=script; nopush","Link: </page-data/app-data.json>; rel=preload; as=fetch; crossorigin; nopush","Link: </page-data/404.html/page-data.json>; rel=preload; as=fetch; crossorigin; nopush"]}